LICENSE
MANIFEST.in
NOTICE
setup.cfg
setup.py
shortwave/__init__.py
shortwave/meta.py
shortwave/transmission.py
shortwave/uri.py
shortwave.egg-info/PKG-INFO
shortwave.egg-info/SOURCES.txt
shortwave.egg-info/dependency_links.txt
shortwave.egg-info/entry_points.txt
shortwave.egg-info/not-zip-safe
shortwave.egg-info/top_level.txt
shortwave/http/__init__.py
shortwave/http/__main__.py
shortwave/http/rfc2616.py
shortwave/messaging/__init__.py
shortwave/messaging/rfc822.py
shortwave/numbers/__init__.py
shortwave/numbers/services.py
shortwave/util/__init__.py
shortwave/util/compat.py
shortwave/util/concurrency.py
shortwave/util/watcher.py
test/test_uri.py